lib/__init__.py
lib/bpctl/__init__.py
lib/bpctl/authenticate.py
lib/bpctl/base.py
lib/bpctl/bp_manifest.py
lib/bpctl/bpctl.py
lib/bpctl/config.py
lib/bpctl/load_data.py
lib/bpctl/read_bp_yaml.py
lib/bpctl/utils.py
bpctl-1.2.dist-info/LICENSE
bpctl-1.2.dist-info/METADATA
bpctl-1.2.dist-info/WHEEL
bpctl-1.2.dist-info/top_level.txt
bpctl-1.2.dist-info/RECORD
